CHANGES.txt
MANIFEST.in
README.md
setup.py
genius/__init__.py
genius/digital.py
genius/loader.py
genius/process.py
genius/tools.py
genius/trie.py
genius/word.py
genius.egg-info/PKG-INFO
genius.egg-info/SOURCES.txt
genius.egg-info/dependency_links.txt
genius.egg-info/requires.txt
genius.egg-info/top_level.txt
genius/library/admin.dic
genius/library/break.regex
genius/library/break.txt
genius/library/combine.regex
genius/library/crf_pos_model.txt
genius/library/crf_seg_model.txt
genius/library/default.dic
genius/library/idf.txt
genius/library/pinyin_tokenizer.dic