Metadata-Version: 1.0
Name: genius
Version: 3.1.3
Summary: genius中文分词 Chinese Segment On linear-chain CRF
Home-page: https://github.com/duanhongyi/genius
Author: duanhongyi
Author-email: duanhyi@gmail.com
License: BSD
Platform: all platform
